dreamboxapi/__init__.py
dreamboxapi/api.py
dreamboxapi/data.py
dreamboxapi-1.0.4.dist-info/LICENSE
dreamboxapi-1.0.4.dist-info/METADATA
dreamboxapi-1.0.4.dist-info/WHEEL
dreamboxapi-1.0.4.dist-info/top_level.txt
dreamboxapi-1.0.4.dist-info/RECORD
