Metadata-Version: 2.1
Name: dreamboxapi
Version: 1.0.4
Summary: Provides a python interface to interact with a dreambox running the official webinterface
Home-page: https://github.com/sreichholf/python-dreamboxapi
Author: Stephan Reichholf
Author-email: reichi@opendreambox.org
License: MIT license
Keywords: dreambox,enigma2
Platform: UNKNOWN
Classifier: Development Status :: 4 - Beta
Classifier: Intended Audience :: Developers
Classifier: License :: OSI Approved :: MIT License
Classifier: Natural Language :: English
Classifier: Programming Language :: Python :: 3.6
Classifier: Programming Language :: Python :: 3.7
Requires-Dist: requests (>=2.21.0)
